[
    {
        "name": "id",
        "dbType": "bigInteger,true,true",
        "htmlType": null,
        "validations": null,
        "searchable": false,
        "fillable": false,
        "primary": true,
        "inForm": false,
        "inIndex": false,
        "inView": false
    },
    {
        "name": "diet_type",
        "dbType": "string",
        "htmlType": "text",
        "validations": "required|string|string|string",
        "searchable": true,
        "fillable": true,
        "primary": false,
        "inForm": true,
        "inIndex": true,
        "inView": true
    },
    {
        "name": "total_calories",
        "dbType": "bigInteger,false",
        "htmlType": null,
        "validations": "required",
        "searchable": true,
        "fillable": true,
        "primary": false,
        "inForm": true,
        "inIndex": true,
        "inView": true
    },
    {
        "name": "breakfast_units",
        "dbType": "bigInteger,false,true",
        "htmlType": null,
        "validations": "required",
        "searchable": true,
        "fillable": true,
        "primary": false,
        "inForm": true,
        "inIndex": true,
        "inView": true
    },
    {
        "name": "lunch_units",
        "dbType": "bigInteger,false,true",
        "htmlType": null,
        "validations": "required",
        "searchable": true,
        "fillable": true,
        "primary": false,
        "inForm": true,
        "inIndex": true,
        "inView": true
    },
    {
        "name": "dinner_units",
        "dbType": "bigInteger,false,true",
        "htmlType": null,
        "validations": "required",
        "searchable": true,
        "fillable": true,
        "primary": false,
        "inForm": true,
        "inIndex": true,
        "inView": true
    },
    {
        "name": "fruit_units",
        "dbType": "bigInteger,false,true",
        "htmlType": null,
        "validations": "required",
        "searchable": true,
        "fillable": true,
        "primary": false,
        "inForm": true,
        "inIndex": true,
        "inView": true
    },
    {
        "name": "snack_units",
        "dbType": "bigInteger,false,true",
        "htmlType": null,
        "validations": "required",
        "searchable": true,
        "fillable": true,
        "primary": false,
        "inForm": true,
        "inIndex": true,
        "inView": true
    },
    {
        "name": "created_at",
        "dbType": "datetime:nullable",
        "htmlType": "date",
        "validations": "nullable|nullable|nullable",
        "searchable": false,
        "fillable": false,
        "primary": false,
        "inForm": false,
        "inIndex": false,
        "inView": false
    },
    {
        "name": "updated_at",
        "dbType": "datetime:nullable",
        "htmlType": "date",
        "validations": "nullable|nullable|nullable",
        "searchable": false,
        "fillable": false,
        "primary": false,
        "inForm": false,
        "inIndex": false,
        "inView": false
    },
    {
        "name": "deleted_at",
        "dbType": "datetime:nullable",
        "htmlType": "date",
        "validations": "nullable|nullable|nullable",
        "searchable": false,
        "fillable": false,
        "primary": false,
        "inForm": false,
        "inIndex": false,
        "inView": false
    }
]